zgent/__init__.py
zgent/core/__init__.py
zgent/core/agent.py
zgent/core/channel.py
zgent/core/client.py
zgent/core/context.py
zgent/core/hook.py
zgent/core/message.py
zgent/core/tool.py
zgent-0.1.0.dist-info/METADATA
zgent-0.1.0.dist-info/WHEEL
zgent-0.1.0.dist-info/RECORD
